noms/__init__.py
noms/analyze.py
noms/food.py
noms/report.py
noms/search.py
noms/client/__init__.py
noms/client/dict_parse.py
noms/client/main.py
noms/objects/__init__.py
noms/objects/food.py
noms/objects/nutrient_dict.py
noms/objects/nutrient_ids.json
noms/service/__init__.py
noms/service/food.py
noms/service/report.py
noms/service/search.py
noms-0.1.7.dist-info/LICENSE
noms-0.1.7.dist-info/METADATA
noms-0.1.7.dist-info/WHEEL
noms-0.1.7.dist-info/top_level.txt
noms-0.1.7.dist-info/RECORD
