Metadata-Version: 2.1
Name: noms
Version: 0.1.7
Summary: A fun and simple Python package that allows you to work with highly detailed nutrition data
Home-page: https://github.com/noahtren/noms
Author: Noah Trenaman
Author-email: hello@noahtrenaman.com
License: UNKNOWN
Platform: UNKNOWN
Classifier: Programming Language :: Python :: 3
Classifier: License :: OSI Approved :: MIT License
Classifier: Operating System :: OS Independent
